simple_rtmw/base.py
simple_rtmw/types.py
simple_rtmw/utils.py
simple_rtmw/wholebody.py
simple_rtmw/detection/__init__.py
simple_rtmw/detection/yolo.py
simple_rtmw/draw/__init__.py
simple_rtmw/draw/config.py
simple_rtmw/draw/detection.py
simple_rtmw/draw/pose.py
simple_rtmw/draw/utils.py
simple_rtmw/pose/__init__.py
simple_rtmw/pose/post.py
simple_rtmw/pose/pre.py
simple_rtmw/pose/rtmpose.py
simple_rtmw-0.1.1.dist-info/licenses/LICENSE
simple_rtmw-0.1.1.dist-info/METADATA
simple_rtmw-0.1.1.dist-info/WHEEL
simple_rtmw-0.1.1.dist-info/top_level.txt
simple_rtmw-0.1.1.dist-info/RECORD
