Metadata-Version: 2.4
Name: simple-rtmw
Version: 0.1.1
Summary: RTMW simple rtmw inference
Author: Ajit Nath
License-Expression: Apache-2.0
Project-URL: Homepage, https://github.com/anath2/simple-rtmw
Project-URL: Repository, https://github.com/anath2/simple-rtmw
Project-URL: Bug Tracker, https://github.com/anath2/simple-rtmw/issues
Keywords: pose estimation,onnx,rtmpose,yolox,computer vision
Classifier: Development Status :: 3 - Alpha
Classifier: Intended Audience :: Developers
Classifier: Programming Language :: Python :: 3
Classifier: Programming Language :: Python :: 3.13
Classifier: Topic :: Scientific/Engineering :: Artificial Intelligence
Classifier: Topic :: Software Development :: Libraries :: Python Modules
Requires-Python: >=3.13
License-File: LICENSE
Requires-Dist: numpy>=2.3.2
Requires-Dist: onnxruntime>=1.22.1
Requires-Dist: opencv-python>=4.11.0.86
Requires-Dist: requests>=2.32.5
Requires-Dist: tqdm>=4.67.1
Dynamic: license-file
